pinaps/__init__.py
pinaps/blinoParser.py
pinaps/callbacks_inprogress.py
pinaps/console_inprogress.py
pinaps/piNapsController.py
pinaps-0.7.5.dist-info/LICENSE
pinaps-0.7.5.dist-info/METADATA
pinaps-0.7.5.dist-info/WHEEL
pinaps-0.7.5.dist-info/top_level.txt
pinaps-0.7.5.dist-info/RECORD
