Metadata-Version: 2.1
Name: pinaps
Version: 0.7.5
Summary: [BETA]Supporting python package for use with the Blino PiNaps Raspberry pi hat.
Home-page: https://bitbucket.org/blino-dev/pinaps/
Author: harri.renney.blino
Author-email: harri.renney@blino.co.uk
License: MIT
Platform: UNKNOWN
Classifier: Programming Language :: Python :: 3
Classifier: License :: OSI Approved :: MIT License
Classifier: Operating System :: OS Independent
Requires-Dist: SC16IS750
Requires-Dist: NeuroParser
